workboxcli
