Metadata-Version: 1.0
Name: workbox-cli
Version: 0.1.4
Summary: A command line interface for Confluence ToolBox
Home-page: http://bitbucket.org/samtardif/workbox-cli
Author: Sam Tardif
Author-email: sam.tardif@gmail.com
License: MIT
Platform: UNKNOWN
